odm2datamodels/__init__.py
odm2datamodels/base.py
odm2datamodels/exceptions.py
odm2datamodels/models/__init__.py
odm2datamodels/models/annotations.py
odm2datamodels/models/auth.py
odm2datamodels/models/core.py
odm2datamodels/models/cv.py
odm2datamodels/models/dataquality.py
odm2datamodels/models/equipment.py
odm2datamodels/models/extensionproperties.py
odm2datamodels/models/externalidentifiers.py
odm2datamodels/models/labanalyses.py
odm2datamodels/models/provenance.py
odm2datamodels/models/results.py
odm2datamodels/models/samplingfeatures.py
odm2datamodels/models/simulation.py
odm2datamodels-0.0.4.dist-info/LICENSE
odm2datamodels-0.0.4.dist-info/METADATA
odm2datamodels-0.0.4.dist-info/WHEEL
odm2datamodels-0.0.4.dist-info/top_level.txt
odm2datamodels-0.0.4.dist-info/RECORD
