Metadata-Version: 2.1
Name: odm2datamodels
Version: 0.0.4
Summary: Collection of object-relational mapping (ORM) data models for ODM2
Home-page: https://github.com/ODM2/ODM2DataModels
Author: ODM2 Team
Author-email: ptomasula@limno.com
Project-URL: bugtracker, https://github.com/ODM2/ODM2DataModels/issues
Keywords: 'Observations Data Model ODM2'
Requires-Python: >=3.8
License-File: LICENSE
Requires-Dist: sqlalchemy (>=1.4.32)
Requires-Dist: pandas (>=1.4)
Requires-Dist: geoalchemy2 (>=0.6.3)
